LICENCE
README.md
pyproject.toml
setup.py
src/preservationeval/__init__.py
src/preservationeval/_version.py
src/preservationeval/const.py
src/preservationeval/core_functions.py
src/preservationeval/eval_functions.py
src/preservationeval/py.typed
src/preservationeval/util_functions.py
src/preservationeval.egg-info/PKG-INFO
src/preservationeval.egg-info/SOURCES.txt
src/preservationeval.egg-info/dependency_links.txt
src/preservationeval.egg-info/requires.txt
src/preservationeval.egg-info/top_level.txt
src/preservationeval/install/__init__.py
src/preservationeval/install/const.py
src/preservationeval/install/export.py
src/preservationeval/install/generate_tables.py
src/preservationeval/install/parse.py
src/preservationeval/install/paths.py
src/preservationeval/install/patterns.py
src/preservationeval/install/py.typed
src/preservationeval/types/__init__.py
src/preservationeval/types/domain_types.py
src/preservationeval/types/exceptions.py
src/preservationeval/types/lookuptable.py
src/preservationeval/types/py.typed
src/preservationeval/utils/__init__.py
src/preservationeval/utils/py.typed
src/preservationeval/utils/safepath.py
src/preservationeval/utils/logging/__init__.py
src/preservationeval/utils/logging/config.py
src/preservationeval/utils/logging/structured.py
tests/test_core.py
tests/test_eval.py
tests/test_util_functions.py
tests/test_utils.py
tests/test_validation.py