Metadata-Version: 2.4
Name: preservationeval
Version: 1.0.0
Summary: A Python implementation of the calculations and evaluations done by the Dew Point Calculator found at https://www.dpcalc.org/.
Author-email: Petter Blomberg <petter.blomberg@gmail.com>
Maintainer-email: Petter Blomberg <petter.blomberg@gmail.com>
Project-URL: Homepage, https://github.com/petter-b/preservationeval
Project-URL: Documentation, https://github.com/petter-b/preservationeval#readme
Project-URL: Repository, https://github.com/petter-b/preservationeval.git
Project-URL: Issues, https://github.com/petter-b/preservationeval/issues
Keywords: preservation,climate,numpy
Classifier: Development Status :: 5 - Production/Stable
Classifier: License :: OSI Approved :: MIT License
Classifier: Programming Language :: Python :: 3
Classifier: Programming Language :: Python :: 3.11
Classifier: Programming Language :: Python :: 3.12
Classifier: Programming Language :: Python :: 3.13
Classifier: Operating System :: OS Independent
Requires-Python: >=3.11
License-File: LICENCE
Requires-Dist: numpy<2.0.0,>=1.26.0
Requires-Dist: requests<3.0.0,>=2.31.0
Provides-Extra: test
Requires-Dist: pytest>=7.4.0; extra == "test"
Requires-Dist: pytest-mypy>=0.10.3; extra == "test"
Requires-Dist: pytest-cov>=4.1.0; extra == "test"
Requires-Dist: pytest-benchmark>=4.0.0; extra == "test"
Requires-Dist: requests-mock>=1.11.0; extra == "test"
Provides-Extra: lint
Requires-Dist: mypy>=1.16.1; extra == "lint"
Requires-Dist: ruff>=0.12.2; extra == "lint"
Requires-Dist: pre-commit>=3.6.0; extra == "lint"
Requires-Dist: types-setuptools>=69.0.0; extra == "lint"
Provides-Extra: profile
Requires-Dist: memory_profiler>=0.61.0; extra == "profile"
Provides-Extra: dev
Requires-Dist: preservationeval[lint,profile,test]; extra == "dev"
Dynamic: license-file
